baa/__init__.py
baa/arlo_api.py
baa/attendee_parser/__init__.py
baa/attendee_parser/butter.py
baa/classes.py
baa/cli.py
baa/exceptions.py
baa/helpers.py
baa/log.py
baa/main.py
baa-0.3.0.dist-info/LICENSE.txt
baa-0.3.0.dist-info/METADATA
baa-0.3.0.dist-info/WHEEL
baa-0.3.0.dist-info/entry_points.txt
baa-0.3.0.dist-info/RECORD
