Metadata-Version: 2.1
Name: baa
Version: 0.3.0
Summary: Command line utility to automate attendance registration in Arlo
Home-page: https://github.com/kish-an/basic-arlo-assistant
License: MIT
Author: Kishan
Author-email: kishan.o@hotmail.com
Requires-Python: >=3.10,<4.0
Classifier: License :: OSI Approved :: MIT License
Classifier: Programming Language :: Python :: 3
Classifier: Programming Language :: Python :: 3.10
Classifier: Programming Language :: Python :: 3.11
Requires-Dist: click (>=8.1.7,<9.0.0)
Requires-Dist: httpx[http2] (>=0.27.2,<0.28.0)
Requires-Dist: keyring (>=25.4.1,<26.0.0)
Requires-Dist: lxml (>=5.3.0,<6.0.0)
Requires-Dist: prettytable (>=3.11.0,<4.0.0)
Project-URL: Repository, https://github.com/kish-an/basic-arlo-assistant
